encommon/__init__.py
encommon/conftest.py
encommon/py.typed
encommon/version.txt
encommon/config/__init__.py
encommon/config/common.py
encommon/config/config.py
encommon/config/files.py
encommon/config/logger.py
encommon/config/params.py
encommon/config/paths.py
encommon/config/test/__init__.py
encommon/config/test/test_common.py
encommon/config/test/test_config.py
encommon/config/test/test_files.py
encommon/config/test/test_logger.py
encommon/config/test/test_paths.py
encommon/crypts/__init__.py
encommon/crypts/crypts.py
encommon/crypts/hashes.py
encommon/crypts/params.py
encommon/crypts/test/__init__.py
encommon/crypts/test/test_crypts.py
encommon/crypts/test/test_hashes.py
encommon/times/__init__.py
encommon/times/common.py
encommon/times/parse.py
encommon/times/timer.py
encommon/times/times.py
encommon/times/window.py
encommon/times/test/__init__.py
encommon/times/test/test_common.py
encommon/times/test/test_parse.py
encommon/times/test/test_timer.py
encommon/times/test/test_times.py
encommon/times/test/test_window.py
encommon/types/__init__.py
encommon/types/dicts.py
encommon/types/empty.py
encommon/types/test/__init__.py
encommon/types/test/test_dicts.py
encommon/types/test/test_empty.py
encommon/utils/__init__.py
encommon/utils/common.py
encommon/utils/paths.py
encommon/utils/regexp.py
encommon/utils/sample.py
encommon/utils/stdout.py
encommon/utils/test/__init__.py
encommon/utils/test/test_paths.py
encommon/utils/test/test_regexp.py
encommon/utils/test/test_sample.py
encommon/utils/test/test_stdout.py
encommon-2.0.2.dist-info/LICENSE
encommon-2.0.2.dist-info/METADATA
encommon-2.0.2.dist-info/WHEEL
encommon-2.0.2.dist-info/top_level.txt
encommon-2.0.2.dist-info/RECORD
