Metadata-Version: 2.1
Name: encommon
Version: 2.0.2
Summary: Enasis Network Common Library
License: MIT
Classifier: Programming Language :: Python :: 3
Classifier: Programming Language :: Python :: 3.10
Classifier: Programming Language :: Python :: 3.11
Requires-Python: >=3.10
License-File: LICENSE
Requires-Dist: croniter
Requires-Dist: cryptography
Requires-Dist: pydantic
Requires-Dist: python-dateutil
Requires-Dist: pyyaml
Requires-Dist: snaptime
